lxml2json/__init__.py
lxml2json/functions.py
lxml2json-0.2.6.dist-info/LICENSE.txt
lxml2json-0.2.6.dist-info/METADATA
lxml2json-0.2.6.dist-info/WHEEL
lxml2json-0.2.6.dist-info/top_level.txt
lxml2json-0.2.6.dist-info/RECORD
