Metadata-Version: 2.1
Name: lxml2json
Version: 0.2.6
Summary: converts XML elements into their JSON equivalent or vice versa
Home-page: https://github.com/rparelius/lxml2json
Author: Robert Parelius
Author-email: rparelius@gmail.com
License: UNKNOWN
Platform: UNKNOWN
Classifier: Programming Language :: Python
Classifier: License :: OSI Approved :: MIT License
Classifier: Operating System :: OS Independent
